{
	"name": "UI_Customization_ColonyRandom",
	"plugin-id": "Sprite",
	"sid": 510838626542566,
	"isGlobal": false,
	"instanceVariables": [],
	"behaviorTypes": [],
	"effectTypes": [],
	"animations": {
		"items": [
			{
				"frames": [
					{
						"width": 65,
						"height": 60,
						"originX": 0.507692,
						"originY": 0.5,
						"originalSource": "E:\\Drive\\Projects\\Adder\\Art\\Customise Buttons\\Dice1.png",
						"exportFormat": "lossless",
						"exportQuality": 0.8,
						"imageSpriteId": 4904836,
						"collisionPoly": {
							"points": [
								0.261538,
								0.283333,
								0.492308,
								0.166667,
								0.753846,
								0.266667,
								0.861538,
								0.5,
								0.8,
								0.783333,
								0.492308,
								0.9,
								0.230769,
								0.75,
								0.2,
								0.5
							]
						},
						"useCollisionPoly": true,
						"duration": 1
					},
					{
						"width": 65,
						"height": 60,
						"originX": 0.507692,
						"originY": 0.5,
						"originalSource": "E:\\Drive\\Projects\\Adder\\Art\\Customise Buttons\\Dice2.png",
						"exportFormat": "lossless",
						"exportQuality": 0.8,
						"imageSpriteId": 3292930,
						"collisionPoly": {
							"points": [
								0.276923,
								0.3,
								0.492308,
								0.183333,
								0.738462,
								0.283333,
								0.861538,
								0.5,
								0.8,
								0.783333,
								0.492308,
								0.916667,
								0.230769,
								0.75,
								0.2,
								0.5
							]
						},
						"useCollisionPoly": true,
						"duration": 1
					}
				],
				"sid": 827235083073759,
				"name": "Default",
				"isLooping": false,
				"isPingPong": false,
				"repeatCount": 1,
				"repeatTo": 0,
				"speed": 0
			}
		],
		"subfolders": []
	}
}