{
	"name": "3",
	"layers": [
		{
			"name": "BG",
			"overriden": 1,
			"instances": [],
			"sid": 812892752003817,
			"effectTypes": [],
			"isInitiallyVisible": true,
			"color": [
				1,
				1,
				1,
				1
			],
			"backgroundColor": [
				0.8588235294117647,
				0.9058823529411765,
				0.9568627450980393,
				1
			],
			"isTransparent": false,
			"parallaxX": 0.05,
			"parallaxY": 1,
			"scaleRate": 1,
			"forceOwnTexture": false,
			"useRenderCells": false,
			"blendMode": "normal",
			"global": false
		},
		{
			"name": "LevelBG",
			"overriden": 0,
			"instances": [
				{
					"type": "Tile_BGA",
					"properties": {
						"initially-visible": true,
						"origin": "top-left",
						"wrap-horizontal": "repeat",
						"wrap-vertical": "repeat",
						"image-offset-x": 0,
						"image-offset-y": 0,
						"image-scale-x": 1,
						"image-scale-y": 1,
						"image-angle": 0
					},
					"uid": 12319,
					"instanceVariables": {},
					"behaviors": {},
					"world": {
						"x": 280,
						"y": 792,
						"width": 256,
						"height": 176,
						"originX": 0,
						"originY": 0,
						"color": [
							1,
							1,
							1,
							1
						],
						"angle": 0,
						"zElevation": 0
					}
				},
				{
					"type": "Tile_FilterOut",
					"properties": {
						"initially-visible": true,
						"initial-animation": "Default",
						"initial-frame": 0,
						"enable-collisions": true,
						"live-preview": false
					},
					"uid": 12321,
					"instanceVariables": {},
					"behaviors": {},
					"world": {
						"x": 296,
						"y": 800,
						"width": 96,
						"height": 48,
						"originX": 0.5,
						"originY": 0.5,
						"color": [
							1,
							1,
							1,
							1
						],
						"angle": 5.803900484179586,
						"zElevation": 0,
						"blendMode": "source-in"
					}
				},
				{
					"type": "Tile_FilterOut",
					"properties": {
						"initially-visible": true,
						"initial-animation": "Default",
						"initial-frame": 0,
						"enable-collisions": true,
						"live-preview": false
					},
					"uid": 12322,
					"instanceVariables": {},
					"behaviors": {},
					"world": {
						"x": 515.436889648,
						"y": 800.775939941,
						"width": 96,
						"height": 48,
						"originX": 0.5,
						"originY": 0.5,
						"color": [
							1,
							1,
							1,
							1
						],
						"angle": 0.444065779,
						"zElevation": 0,
						"blendMode": "source-in"
					}
				},
				{
					"type": "Tile_FilterOut",
					"properties": {
						"initially-visible": true,
						"initial-animation": "Default",
						"initial-frame": 0,
						"enable-collisions": true,
						"live-preview": false
					},
					"uid": 12323,
					"instanceVariables": {},
					"behaviors": {},
					"world": {
						"x": 552,
						"y": 924,
						"width": 88,
						"height": 32,
						"originX": 0.5,
						"originY": 0.5,
						"color": [
							1,
							1,
							1,
							1
						],
						"angle": 4.712388936179586,
						"zElevation": 0,
						"blendMode": "source-in"
					}
				},
				{
					"type": "Tile_FilterOut",
					"properties": {
						"initially-visible": true,
						"initial-animation": "Default",
						"initial-frame": 0,
						"enable-collisions": true,
						"live-preview": false
					},
					"uid": 12324,
					"instanceVariables": {},
					"behaviors": {},
					"world": {
						"x": 264,
						"y": 928,
						"width": 80,
						"height": 32,
						"originX": 0.5,
						"originY": 0.5,
						"color": [
							1,
							1,
							1,
							1
						],
						"angle": 4.712388936179586,
						"zElevation": 0,
						"blendMode": "source-in"
					}
				},
				{
					"type": "Tile_FilterOut",
					"properties": {
						"initially-visible": true,
						"initial-animation": "Default",
						"initial-frame": 0,
						"enable-collisions": true,
						"live-preview": false
					},
					"uid": 12583,
					"instanceVariables": {},
					"behaviors": {},
					"world": {
						"x": 544,
						"y": 856,
						"width": 56,
						"height": 32,
						"originX": 0.5,
						"originY": 0.5,
						"color": [
							1,
							1,
							1,
							1
						],
						"angle": 4.712388936179586,
						"zElevation": 0,
						"blendMode": "source-in"
					}
				},
				{
					"type": "Tile_FilterOut",
					"properties": {
						"initially-visible": true,
						"initial-animation": "Default",
						"initial-frame": 0,
						"enable-collisions": true,
						"live-preview": false
					},
					"uid": 12584,
					"instanceVariables": {},
					"behaviors": {},
					"world": {
						"x": 272,
						"y": 864,
						"width": 56,
						"height": 32,
						"originX": 0.5,
						"originY": 0.5,
						"color": [
							1,
							1,
							1,
							1
						],
						"angle": 4.712388936179586,
						"zElevation": 0,
						"blendMode": "source-in"
					}
				},
				{
					"type": "Tile_FilterOut",
					"properties": {
						"initially-visible": true,
						"initial-animation": "Default",
						"initial-frame": 0,
						"enable-collisions": true,
						"live-preview": false
					},
					"uid": 12618,
					"instanceVariables": {},
					"behaviors": {},
					"world": {
						"x": 412,
						"y": 788,
						"width": 152,
						"height": 24,
						"originX": 0.5,
						"originY": 0.5,
						"color": [
							1,
							1,
							1,
							1
						],
						"angle": 0,
						"zElevation": 0,
						"blendMode": "source-in"
					}
				}
			],
			"sid": 259110749698199,
			"effectTypes": [],
			"isInitiallyVisible": true,
			"color": [
				1,
				1,
				1,
				1
			],
			"backgroundColor": [
				1,
				1,
				1,
				1
			],
			"isTransparent": true,
			"parallaxX": 1,
			"parallaxY": 1,
			"scaleRate": 1,
			"forceOwnTexture": true,
			"useRenderCells": false,
			"blendMode": "normal",
			"global": false
		},
		{
			"name": "Level",
			"overriden": 0,
			"instances": [
				{
					"type": "Tile_FloorA",
					"properties": {
						"initially-visible": true,
						"origin": "top-left",
						"wrap-horizontal": "repeat",
						"wrap-vertical": "repeat",
						"image-offset-x": 0,
						"image-offset-y": 0,
						"image-scale-x": 1,
						"image-scale-y": 1,
						"image-angle": 0
					},
					"uid": 12332,
					"instanceVariables": {},
					"behaviors": {},
					"world": {
						"x": 288,
						"y": 968,
						"width": 240,
						"height": 8,
						"originX": 0,
						"originY": 0,
						"color": [
							1,
							1,
							1,
							1
						],
						"angle": 0,
						"zElevation": 0
					}
				},
				{
					"type": "Tile_Shadow",
					"properties": {
						"initially-visible": true,
						"initial-animation": "Default",
						"initial-frame": 0,
						"enable-collisions": true,
						"live-preview": false
					},
					"uid": 12333,
					"instanceVariables": {
						"InitialFrame": 0
					},
					"behaviors": {},
					"world": {
						"x": 344,
						"y": 847,
						"width": 128,
						"height": 40,
						"originX": 0,
						"originY": 1,
						"color": [
							1,
							1,
							1,
							1
						],
						"angle": 0,
						"zElevation": 0
					}
				},
				{
					"type": "Tile_Shadow",
					"properties": {
						"initially-visible": true,
						"initial-animation": "Default",
						"initial-frame": 4,
						"enable-collisions": true,
						"live-preview": false
					},
					"uid": 12334,
					"instanceVariables": {
						"InitialFrame": 4
					},
					"behaviors": {},
					"world": {
						"x": 304,
						"y": 840,
						"width": 16,
						"height": 32,
						"originX": 0.5,
						"originY": 0.5,
						"color": [
							1,
							1,
							1,
							1
						],
						"angle": 0,
						"zElevation": 0
					}
				},
				{
					"type": "Tile_Shadow",
					"properties": {
						"initially-visible": true,
						"initial-animation": "Default",
						"initial-frame": 4,
						"enable-collisions": true,
						"live-preview": false
					},
					"uid": 12335,
					"instanceVariables": {
						"InitialFrame": 4
					},
					"behaviors": {},
					"world": {
						"x": 320,
						"y": 832,
						"width": 16,
						"height": 32,
						"originX": 0.5,
						"originY": 0.5,
						"color": [
							1,
							1,
							1,
							1
						],
						"angle": 0,
						"zElevation": 0
					}
				},
				{
					"type": "Tile_Shadow",
					"properties": {
						"initially-visible": true,
						"initial-animation": "Default",
						"initial-frame": 4,
						"enable-collisions": true,
						"live-preview": false
					},
					"uid": 12336,
					"instanceVariables": {
						"InitialFrame": 4
					},
					"behaviors": {},
					"world": {
						"x": 336,
						"y": 824,
						"width": 16,
						"height": 32,
						"originX": 0.5,
						"originY": 0.5,
						"color": [
							1,
							1,
							1,
							1
						],
						"angle": 0,
						"zElevation": 0
					}
				},
				{
					"type": "Tile_Shadow",
					"properties": {
						"initially-visible": true,
						"initial-animation": "Default",
						"initial-frame": 12,
						"enable-collisions": true,
						"live-preview": false
					},
					"uid": 12337,
					"instanceVariables": {
						"InitialFrame": 12
					},
					"behaviors": {},
					"world": {
						"x": 278,
						"y": 848,
						"width": 8,
						"height": 32,
						"originX": -1.25,
						"originY": 0.5,
						"color": [
							1,
							1,
							1,
							1
						],
						"angle": 0,
						"zElevation": 0
					}
				},
				{
					"type": "Tile_Shadow",
					"properties": {
						"initially-visible": true,
						"initial-animation": "Default",
						"initial-frame": 5,
						"enable-collisions": true,
						"live-preview": false
					},
					"uid": 12338,
					"instanceVariables": {
						"InitialFrame": 5
					},
					"behaviors": {},
					"world": {
						"x": 480,
						"y": 824,
						"width": 16,
						"height": 32,
						"originX": 0.5,
						"originY": 0.5,
						"color": [
							1,
							1,
							1,
							1
						],
						"angle": 0,
						"zElevation": 0
					}
				},
				{
					"type": "Tile_Shadow",
					"properties": {
						"initially-visible": true,
						"initial-animation": "Default",
						"initial-frame": 5,
						"enable-collisions": true,
						"live-preview": false
					},
					"uid": 12339,
					"instanceVariables": {
						"InitialFrame": 5
					},
					"behaviors": {},
					"world": {
						"x": 496,
						"y": 832,
						"width": 16,
						"height": 32,
						"originX": 0.5,
						"originY": 0.5,
						"color": [
							1,
							1,
							1,
							1
						],
						"angle": 0,
						"zElevation": 0
					}
				},
				{
					"type": "Tile_Shadow",
					"properties": {
						"initially-visible": true,
						"initial-animation": "Default",
						"initial-frame": 5,
						"enable-collisions": true,
						"live-preview": false
					},
					"uid": 12340,
					"instanceVariables": {
						"InitialFrame": 5
					},
					"behaviors": {},
					"world": {
						"x": 512,
						"y": 840,
						"width": 16,
						"height": 32,
						"originX": 0.5,
						"originY": 0.5,
						"color": [
							1,
							1,
							1,
							1
						],
						"angle": 0,
						"zElevation": 0
					}
				},
				{
					"type": "Tile_Shadow",
					"properties": {
						"initially-visible": true,
						"initial-animation": "Default",
						"initial-frame": 13,
						"enable-collisions": true,
						"live-preview": false
					},
					"uid": 12341,
					"instanceVariables": {
						"InitialFrame": 13
					},
					"behaviors": {},
					"world": {
						"x": 538,
						"y": 848,
						"width": 8,
						"height": 32,
						"originX": 2.25,
						"originY": 0.5,
						"color": [
							1,
							1,
							1,
							1
						],
						"angle": 0,
						"zElevation": 0
					}
				},
				{
					"type": "Door",
					"properties": {
						"initially-visible": true,
						"initial-animation": "WoodClosed",
						"initial-frame": 0,
						"enable-collisions": true,
						"live-preview": false
					},
					"uid": 12342,
					"instanceVariables": {
						"TargetForm": "Tile_Door",
						"OutlineCopy": false,
						"Outlined": false,
						"zzzNearest": false,
						"DiagUID": 0,
						"DiagText": "",
						"DiagTag": "",
						"DiagIndex": 0,
						"DiagWait": 0,
						"DiagStarted": 0,
						"zzzDiagCanInteract": 0,
						"zzzzNearest": false,
						"DestroyAfterDiag": false,
						"WorldEnabled": true,
						"WorldBark": "",
						"WorldHoverOutline": true,
						"WorldHoverText": "",
						"WorldCanInteract": false,
						"WorldTouched": false,
						"WorldInteractType": "modify",
						"Type": "Wood",
						"OriginalX": 0,
						"OriginalY": 0,
						"HP": 10,
						"Closed": true,
						"MaxHP": 10,
						"RangeID": 0,
						"Locked": false
					},
					"behaviors": {
						"Diag_Fade": {
							"properties": {
								"fade-in-time": 0,
								"wait-time": 0,
								"fade-out-time": 0.5,
								"destroy": true,
								"enabled": false,
								"live-preview": false
							}
						},
						"Solid": {
							"properties": {
								"enabled": true,
								"tags": ""
							}
						},
						"Physics": {
							"properties": {
								"immovable": true,
								"collision-mask": "use-collision-polygon",
								"prevent-rotation": false,
								"density": 1,
								"friction": 0.5,
								"elasticity": 0.2,
								"linear-damping": 0,
								"angular-damping": 0.01,
								"bullet": false,
								"enabled": true
							}
						}
					},
					"effects": {
						"Outline": {
							"parameters": {
								"Just outline": 0,
								"Width": 1,
								"Color": [
									1,
									1,
									1,
									1
								]
							}
						}
					},
					"world": {
						"x": 288,
						"y": 968,
						"width": -12,
						"height": 58,
						"originX": 0.166667,
						"originY": 0.982759,
						"color": [
							1,
							1,
							1,
							1
						],
						"angle": 0,
						"zElevation": 0
					}
				},
				{
					"type": "Tile_Wall",
					"properties": {
						"initially-visible": true,
						"initial-animation": "Default",
						"initial-frame": 2,
						"enable-collisions": true,
						"live-preview": false
					},
					"uid": 12343,
					"instanceVariables": {
						"InitialFrame": 2
					},
					"behaviors": {},
					"world": {
						"x": 280,
						"y": 848,
						"width": 8,
						"height": 8,
						"originX": 0,
						"originY": 1,
						"color": [
							1,
							1,
							1,
							1
						],
						"angle": 0,
						"zElevation": 0
					}
				},
				{
					"type": "Tile_Wall",
					"properties": {
						"initially-visible": true,
						"initial-animation": "Default",
						"initial-frame": 22,
						"enable-collisions": true,
						"live-preview": false
					},
					"uid": 12344,
					"instanceVariables": {
						"InitialFrame": 22
					},
					"behaviors": {},
					"world": {
						"x": 280,
						"y": 840,
						"width": 8,
						"height": 8,
						"originX": 0,
						"originY": 1,
						"color": [
							1,
							1,
							1,
							1
						],
						"angle": 0,
						"zElevation": 0
					}
				},
				{
					"type": "Tile_Wall",
					"properties": {
						"initially-visible": true,
						"initial-animation": "Default",
						"initial-frame": 17,
						"enable-collisions": true,
						"live-preview": false
					},
					"uid": 12345,
					"instanceVariables": {
						"InitialFrame": 17
					},
					"behaviors": {},
					"world": {
						"x": 528,
						"y": 976,
						"width": 8,
						"height": 8,
						"originX": 0,
						"originY": 1,
						"color": [
							1,
							1,
							1,
							1
						],
						"angle": 0,
						"zElevation": 0
					}
				},
				{
					"type": "Tile_Wall",
					"properties": {
						"initially-visible": true,
						"initial-animation": "Default",
						"initial-frame": 16,
						"enable-collisions": true,
						"live-preview": false
					},
					"uid": 12346,
					"instanceVariables": {
						"InitialFrame": 16
					},
					"behaviors": {},
					"world": {
						"x": 280,
						"y": 976,
						"width": 8,
						"height": 8,
						"originX": 0,
						"originY": 1,
						"color": [
							1,
							1,
							1,
							1
						],
						"angle": 0,
						"zElevation": 0
					}
				},
				{
					"type": "Tile_Roof",
					"properties": {
						"initially-visible": true,
						"initial-animation": "Default",
						"initial-frame": 10,
						"enable-collisions": true,
						"live-preview": false
					},
					"uid": 12347,
					"instanceVariables": {
						"InitialFrame": 10
					},
					"behaviors": {},
					"world": {
						"x": 296,
						"y": 832,
						"width": 16,
						"height": 16,
						"originX": 0,
						"originY": 1,
						"color": [
							1,
							1,
							1,
							1
						],
						"angle": 0,
						"zElevation": 0
					}
				},
				{
					"type": "Tile_Roof",
					"properties": {
						"initially-visible": true,
						"initial-animation": "Default",
						"initial-frame": 10,
						"enable-collisions": true,
						"live-preview": false
					},
					"uid": 12348,
					"instanceVariables": {
						"InitialFrame": 10
					},
					"behaviors": {},
					"world": {
						"x": 312,
						"y": 824,
						"width": 16,
						"height": 16,
						"originX": 0,
						"originY": 1,
						"color": [
							1,
							1,
							1,
							1
						],
						"angle": 0,
						"zElevation": 0
					}
				},
				{
					"type": "Tile_Roof",
					"properties": {
						"initially-visible": true,
						"initial-animation": "Default",
						"initial-frame": 10,
						"enable-collisions": true,
						"live-preview": false
					},
					"uid": 12349,
					"instanceVariables": {
						"InitialFrame": 10
					},
					"behaviors": {},
					"world": {
						"x": 328,
						"y": 816,
						"width": 16,
						"height": 16,
						"originX": 0,
						"originY": 1,
						"color": [
							1,
							1,
							1,
							1
						],
						"angle": 0,
						"zElevation": 0
					}
				},
				{
					"type": "Tile_Roof",
					"properties": {
						"initially-visible": true,
						"initial-animation": "Default",
						"initial-frame": 1,
						"enable-collisions": true,
						"live-preview": false
					},
					"uid": 12350,
					"instanceVariables": {
						"InitialFrame": 1
					},
					"behaviors": {},
					"world": {
						"x": 344,
						"y": 816,
						"width": 16,
						"height": 16,
						"originX": 0,
						"originY": 1,
						"color": [
							1,
							1,
							1,
							1
						],
						"angle": 0,
						"zElevation": 0
					}
				},
				{
					"type": "Tile_Roof",
					"properties": {
						"initially-visible": true,
						"initial-animation": "Default",
						"initial-frame": 1,
						"enable-collisions": true,
						"live-preview": false
					},
					"uid": 12369,
					"instanceVariables": {
						"InitialFrame": 1
					},
					"behaviors": {},
					"world": {
						"x": 360,
						"y": 816,
						"width": 16,
						"height": 16,
						"originX": 0,
						"originY": 1,
						"color": [
							1,
							1,
							1,
							1
						],
						"angle": 0,
						"zElevation": 0
					}
				},
				{
					"type": "Tile_Roof",
					"properties": {
						"initially-visible": true,
						"initial-animation": "Default",
						"initial-frame": 1,
						"enable-collisions": true,
						"live-preview": false
					},
					"uid": 12396,
					"instanceVariables": {
						"InitialFrame": 1
					},
					"behaviors": {},
					"world": {
						"x": 376,
						"y": 816,
						"width": 16,
						"height": 16,
						"originX": 0,
						"originY": 1,
						"color": [
							1,
							1,
							1,
							1
						],
						"angle": 0,
						"zElevation": 0
					}
				},
				{
					"type": "Tile_Roof",
					"properties": {
						"initially-visible": true,
						"initial-animation": "Default",
						"initial-frame": 1,
						"enable-collisions": true,
						"live-preview": false
					},
					"uid": 12446,
					"instanceVariables": {
						"InitialFrame": 1
					},
					"behaviors": {},
					"world": {
						"x": 392,
						"y": 816,
						"width": 16,
						"height": 16,
						"originX": 0,
						"originY": 1,
						"color": [
							1,
							1,
							1,
							1
						],
						"angle": 0,
						"zElevation": 0
					}
				},
				{
					"type": "Tile_Roof",
					"properties": {
						"initially-visible": true,
						"initial-animation": "Default",
						"initial-frame": 11,
						"enable-collisions": true,
						"live-preview": false
					},
					"uid": 12452,
					"instanceVariables": {
						"InitialFrame": 11
					},
					"behaviors": {},
					"world": {
						"x": 472,
						"y": 816,
						"width": 16,
						"height": 16,
						"originX": 0,
						"originY": 1,
						"color": [
							1,
							1,
							1,
							1
						],
						"angle": 0,
						"zElevation": 0
					}
				},
				{
					"type": "Tile_Roof",
					"properties": {
						"initially-visible": true,
						"initial-animation": "Default",
						"initial-frame": 11,
						"enable-collisions": true,
						"live-preview": false
					},
					"uid": 12481,
					"instanceVariables": {
						"InitialFrame": 11
					},
					"behaviors": {},
					"world": {
						"x": 488,
						"y": 824,
						"width": 16,
						"height": 16,
						"originX": 0,
						"originY": 1,
						"color": [
							1,
							1,
							1,
							1
						],
						"angle": 0,
						"zElevation": 0
					}
				},
				{
					"type": "Tile_Roof",
					"properties": {
						"initially-visible": true,
						"initial-animation": "Default",
						"initial-frame": 11,
						"enable-collisions": true,
						"live-preview": false
					},
					"uid": 12484,
					"instanceVariables": {
						"InitialFrame": 11
					},
					"behaviors": {},
					"world": {
						"x": 504,
						"y": 832,
						"width": 16,
						"height": 16,
						"originX": 0,
						"originY": 1,
						"color": [
							1,
							1,
							1,
							1
						],
						"angle": 0,
						"zElevation": 0
					}
				},
				{
					"type": "Tile_Roof",
					"properties": {
						"initially-visible": true,
						"initial-animation": "Default",
						"initial-frame": 1,
						"enable-collisions": true,
						"live-preview": false
					},
					"uid": 12485,
					"instanceVariables": {
						"InitialFrame": 1
					},
					"behaviors": {},
					"world": {
						"x": 408,
						"y": 816,
						"width": 16,
						"height": 16,
						"originX": 0,
						"originY": 1,
						"color": [
							1,
							1,
							1,
							1
						],
						"angle": 0,
						"zElevation": 0
					}
				},
				{
					"type": "Tile_Roof",
					"properties": {
						"initially-visible": true,
						"initial-animation": "Default",
						"initial-frame": 1,
						"enable-collisions": true,
						"live-preview": false
					},
					"uid": 12486,
					"instanceVariables": {
						"InitialFrame": 1
					},
					"behaviors": {},
					"world": {
						"x": 424,
						"y": 816,
						"width": 16,
						"height": 16,
						"originX": 0,
						"originY": 1,
						"color": [
							1,
							1,
							1,
							1
						],
						"angle": 0,
						"zElevation": 0
					}
				},
				{
					"type": "Tile_Roof",
					"properties": {
						"initially-visible": true,
						"initial-animation": "Default",
						"initial-frame": 1,
						"enable-collisions": true,
						"live-preview": false
					},
					"uid": 12487,
					"instanceVariables": {
						"InitialFrame": 1
					},
					"behaviors": {},
					"world": {
						"x": 440,
						"y": 816,
						"width": 16,
						"height": 16,
						"originX": 0,
						"originY": 1,
						"color": [
							1,
							1,
							1,
							1
						],
						"angle": 0,
						"zElevation": 0
					}
				},
				{
					"type": "Tile_Roof",
					"properties": {
						"initially-visible": true,
						"initial-animation": "Default",
						"initial-frame": 1,
						"enable-collisions": true,
						"live-preview": false
					},
					"uid": 12488,
					"instanceVariables": {
						"InitialFrame": 1
					},
					"behaviors": {},
					"world": {
						"x": 456,
						"y": 816,
						"width": 16,
						"height": 16,
						"originX": 0,
						"originY": 1,
						"color": [
							1,
							1,
							1,
							1
						],
						"angle": 0,
						"zElevation": 0
					}
				},
				{
					"type": "Door",
					"properties": {
						"initially-visible": true,
						"initial-animation": "WoodClosed",
						"initial-frame": 0,
						"enable-collisions": true,
						"live-preview": false
					},
					"uid": 12489,
					"instanceVariables": {
						"TargetForm": "Tile_Door",
						"OutlineCopy": false,
						"Outlined": false,
						"zzzNearest": false,
						"DiagUID": 0,
						"DiagText": "",
						"DiagTag": "",
						"DiagIndex": 0,
						"DiagWait": 0,
						"DiagStarted": 0,
						"zzzDiagCanInteract": 0,
						"zzzzNearest": false,
						"DestroyAfterDiag": false,
						"WorldEnabled": true,
						"WorldBark": "",
						"WorldHoverOutline": true,
						"WorldHoverText": "",
						"WorldCanInteract": false,
						"WorldTouched": false,
						"WorldInteractType": "modify",
						"Type": "Wood",
						"OriginalX": 0,
						"OriginalY": 0,
						"HP": 10,
						"Closed": true,
						"MaxHP": 10,
						"RangeID": 0,
						"Locked": false
					},
					"behaviors": {
						"Diag_Fade": {
							"properties": {
								"fade-in-time": 0,
								"wait-time": 0,
								"fade-out-time": 0.5,
								"destroy": true,
								"enabled": false,
								"live-preview": false
							}
						},
						"Solid": {
							"properties": {
								"enabled": true,
								"tags": ""
							}
						},
						"Physics": {
							"properties": {
								"immovable": true,
								"collision-mask": "use-collision-polygon",
								"prevent-rotation": false,
								"density": 1,
								"friction": 0.5,
								"elasticity": 0.2,
								"linear-damping": 0,
								"angular-damping": 0.01,
								"bullet": false,
								"enabled": true
							}
						}
					},
					"effects": {
						"Outline": {
							"parameters": {
								"Just outline": 0,
								"Width": 1,
								"Color": [
									1,
									1,
									1,
									1
								]
							}
						}
					},
					"world": {
						"x": 528,
						"y": 968,
						"width": 12,
						"height": 58,
						"originX": 0.166667,
						"originY": 0.982759,
						"color": [
							1,
							1,
							1,
							1
						],
						"angle": 0,
						"zElevation": 0
					}
				},
				{
					"type": "Tile_Wall",
					"properties": {
						"initially-visible": true,
						"initial-animation": "Default",
						"initial-frame": 3,
						"enable-collisions": true,
						"live-preview": false
					},
					"uid": 12490,
					"instanceVariables": {
						"InitialFrame": 3
					},
					"behaviors": {},
					"world": {
						"x": 528,
						"y": 848,
						"width": 8,
						"height": 8,
						"originX": 0,
						"originY": 1,
						"color": [
							1,
							1,
							1,
							1
						],
						"angle": 0,
						"zElevation": 0
					}
				},
				{
					"type": "Tile_Wall",
					"properties": {
						"initially-visible": true,
						"initial-animation": "Default",
						"initial-frame": 7,
						"enable-collisions": true,
						"live-preview": false
					},
					"uid": 12530,
					"instanceVariables": {
						"InitialFrame": 7
					},
					"behaviors": {},
					"world": {
						"x": 528,
						"y": 840,
						"width": 8,
						"height": 8,
						"originX": 0,
						"originY": 1,
						"color": [
							1,
							1,
							1,
							1
						],
						"angle": 0,
						"zElevation": 0
					}
				},
				{
					"type": "Tile_Wall",
					"properties": {
						"initially-visible": true,
						"initial-animation": "Default",
						"initial-frame": 57,
						"enable-collisions": true,
						"live-preview": false
					},
					"uid": 12531,
					"instanceVariables": {
						"InitialFrame": 57
					},
					"behaviors": {},
					"world": {
						"x": 512,
						"y": 896,
						"width": -24,
						"height": 49,
						"originX": 0,
						"originY": 1,
						"color": [
							1,
							1,
							1,
							1
						],
						"angle": 0,
						"zElevation": 0
					}
				},
				{
					"type": "Tile_Wall",
					"properties": {
						"initially-visible": true,
						"initial-animation": "Default",
						"initial-frame": 72,
						"enable-collisions": true,
						"live-preview": false
					},
					"uid": 12539,
					"instanceVariables": {
						"InitialFrame": 72
					},
					"behaviors": {},
					"world": {
						"x": 336,
						"y": 880,
						"width": 32,
						"height": 34,
						"originX": 0,
						"originY": 1,
						"color": [
							1,
							1,
							1,
							1
						],
						"angle": 0,
						"zElevation": 0
					}
				},
				{
					"type": "Tile_Wall",
					"properties": {
						"initially-visible": true,
						"initial-animation": "Default",
						"initial-frame": 49,
						"enable-collisions": true,
						"live-preview": false
					},
					"uid": 12540,
					"instanceVariables": {
						"InitialFrame": 49
					},
					"behaviors": {},
					"world": {
						"x": 408,
						"y": 807,
						"width": 27,
						"height": 48,
						"originX": 0.481481,
						"originY": 0,
						"color": [
							1,
							1,
							1,
							1
						],
						"angle": 0,
						"zElevation": 0
					}
				},
				{
					"type": "Tile_Wall",
					"properties": {
						"initially-visible": true,
						"initial-animation": "Default",
						"initial-frame": 43,
						"enable-collisions": true,
						"live-preview": false
					},
					"uid": 12541,
					"instanceVariables": {
						"InitialFrame": 43
					},
					"behaviors": {},
					"world": {
						"x": 312,
						"y": 896,
						"width": 22,
						"height": 29,
						"originX": 0,
						"originY": 1,
						"color": [
							1,
							1,
							1,
							1
						],
						"angle": 0,
						"zElevation": 0
					}
				},
				{
					"type": "Tile_Wall",
					"properties": {
						"initially-visible": true,
						"initial-animation": "Default",
						"initial-frame": 45,
						"enable-collisions": true,
						"live-preview": false
					},
					"uid": 12542,
					"instanceVariables": {
						"InitialFrame": 45
					},
					"behaviors": {},
					"world": {
						"x": 464,
						"y": 896,
						"width": 20,
						"height": 15,
						"originX": 0,
						"originY": 1,
						"color": [
							1,
							1,
							1,
							1
						],
						"angle": 0,
						"zElevation": 0
					}
				},
				{
					"type": "Tile_Wall",
					"properties": {
						"initially-visible": true,
						"initial-animation": "Default",
						"initial-frame": 45,
						"enable-collisions": true,
						"live-preview": false
					},
					"uid": 12543,
					"instanceVariables": {
						"InitialFrame": 45
					},
					"behaviors": {},
					"world": {
						"x": 448,
						"y": 896,
						"width": 20,
						"height": 15,
						"originX": 0,
						"originY": 1,
						"color": [
							1,
							1,
							1,
							1
						],
						"angle": 0,
						"zElevation": 0
					}
				},
				{
					"type": "Tile_Wall",
					"properties": {
						"initially-visible": true,
						"initial-animation": "Default",
						"initial-frame": 77,
						"enable-collisions": true,
						"live-preview": false
					},
					"uid": 12544,
					"instanceVariables": {
						"InitialFrame": 77
					},
					"behaviors": {},
					"world": {
						"x": 456,
						"y": 872,
						"width": 17,
						"height": 16,
						"originX": 0,
						"originY": 1,
						"color": [
							1,
							1,
							1,
							1
						],
						"angle": 0,
						"zElevation": 0
					}
				},
				{
					"type": "Tile_Wall",
					"properties": {
						"initially-visible": true,
						"initial-animation": "Default",
						"initial-frame": 85,
						"enable-collisions": true,
						"live-preview": false
					},
					"uid": 12545,
					"instanceVariables": {
						"InitialFrame": 85
					},
					"behaviors": {},
					"world": {
						"x": 492,
						"y": 892,
						"width": 12,
						"height": 7,
						"originX": 0.0833333,
						"originY": 1,
						"color": [
							1,
							1,
							1,
							1
						],
						"angle": 0,
						"zElevation": 0
					}
				},
				{
					"type": "Tile_Wall",
					"properties": {
						"initially-visible": true,
						"initial-animation": "Default",
						"initial-frame": 81,
						"enable-collisions": true,
						"live-preview": false
					},
					"uid": 12546,
					"instanceVariables": {
						"InitialFrame": 81
					},
					"behaviors": {},
					"world": {
						"x": 494,
						"y": 863,
						"width": 7,
						"height": 10,
						"originX": 0,
						"originY": 1,
						"color": [
							1,
							1,
							1,
							1
						],
						"angle": 0,
						"zElevation": 0
					}
				},
				{
					"type": "Tile_Roof",
					"properties": {
						"initially-visible": true,
						"initial-animation": "Default",
						"initial-frame": 12,
						"enable-collisions": true,
						"live-preview": false
					},
					"uid": 12549,
					"instanceVariables": {
						"InitialFrame": 12
					},
					"behaviors": {},
					"world": {
						"x": 536,
						"y": 848,
						"width": 16,
						"height": 16,
						"originX": 0,
						"originY": 1,
						"color": [
							1,
							1,
							1,
							1
						],
						"angle": 0,
						"zElevation": 0
					}
				},
				{
					"type": "Tile_Roof",
					"properties": {
						"initially-visible": true,
						"initial-animation": "Default",
						"initial-frame": 11,
						"enable-collisions": true,
						"live-preview": false
					},
					"uid": 12550,
					"instanceVariables": {
						"InitialFrame": 11
					},
					"behaviors": {},
					"world": {
						"x": 520,
						"y": 840,
						"width": 16,
						"height": 16,
						"originX": 0,
						"originY": 1,
						"color": [
							1,
							1,
							1,
							1
						],
						"angle": 0,
						"zElevation": 0
					}
				},
				{
					"type": "Tile_Roof",
					"properties": {
						"initially-visible": true,
						"initial-animation": "Default",
						"initial-frame": 9,
						"enable-collisions": true,
						"live-preview": false
					},
					"uid": 12551,
					"instanceVariables": {
						"InitialFrame": 9
					},
					"behaviors": {},
					"world": {
						"x": 264,
						"y": 848,
						"width": 16,
						"height": 16,
						"originX": 0,
						"originY": 1,
						"color": [
							1,
							1,
							1,
							1
						],
						"angle": 0,
						"zElevation": 0
					}
				},
				{
					"type": "Tile_Roof",
					"properties": {
						"initially-visible": true,
						"initial-animation": "Default",
						"initial-frame": 10,
						"enable-collisions": true,
						"live-preview": false
					},
					"uid": 12552,
					"instanceVariables": {
						"InitialFrame": 10
					},
					"behaviors": {},
					"world": {
						"x": 280,
						"y": 840,
						"width": 16,
						"height": 16,
						"originX": 0,
						"originY": 1,
						"color": [
							1,
							1,
							1,
							1
						],
						"angle": 0,
						"zElevation": 0
					}
				},
				{
					"type": "Tile_Wall",
					"properties": {
						"initially-visible": true,
						"initial-animation": "Default",
						"initial-frame": 2,
						"enable-collisions": true,
						"live-preview": false
					},
					"uid": 12561,
					"instanceVariables": {
						"InitialFrame": 2
					},
					"behaviors": {},
					"world": {
						"x": 280,
						"y": 912,
						"width": 8,
						"height": 8,
						"originX": 0,
						"originY": 1,
						"color": [
							1,
							1,
							1,
							1
						],
						"angle": 0,
						"zElevation": 0
					}
				},
				{
					"type": "Tile_Wall",
					"properties": {
						"initially-visible": true,
						"initial-animation": "Default",
						"initial-frame": 22,
						"enable-collisions": true,
						"live-preview": false
					},
					"uid": 12562,
					"instanceVariables": {
						"InitialFrame": 22
					},
					"behaviors": {},
					"world": {
						"x": 280,
						"y": 904,
						"width": 8,
						"height": 8,
						"originX": 0,
						"originY": 1,
						"color": [
							1,
							1,
							1,
							1
						],
						"angle": 0,
						"zElevation": 0
					}
				},
				{
					"type": "Tile_Ladder",
					"properties": {
						"initially-visible": true,
						"initial-animation": "Wood",
						"initial-frame": 0,
						"enable-collisions": true,
						"live-preview": false
					},
					"uid": 12565,
					"instanceVariables": {
						"Type": "Wood"
					},
					"behaviors": {},
					"world": {
						"x": 392,
						"y": 960,
						"width": 32,
						"height": 32,
						"originX": 0,
						"originY": 0.96875,
						"color": [
							1,
							1,
							1,
							1
						],
						"angle": 0,
						"zElevation": 0
					}
				},
				{
					"type": "Tile_FloorC",
					"properties": {
						"initially-visible": true,
						"origin": "top-left",
						"wrap-horizontal": "repeat",
						"wrap-vertical": "repeat",
						"image-offset-x": 0,
						"image-offset-y": 0,
						"image-scale-x": 1,
						"image-scale-y": 1,
						"image-angle": 0
					},
					"uid": 6353,
					"instanceVariables": {},
					"behaviors": {},
					"world": {
						"x": 288,
						"y": 896,
						"width": 240,
						"height": 8,
						"originX": 0,
						"originY": 0,
						"color": [
							1,
							1,
							1,
							1
						],
						"angle": 0,
						"zElevation": 0
					}
				},
				{
					"type": "Tile_LadderTop",
					"properties": {
						"initially-visible": true,
						"initial-animation": "Wood",
						"initial-frame": 0,
						"enable-collisions": true,
						"live-preview": false
					},
					"uid": 12566,
					"instanceVariables": {
						"Type": "Wood"
					},
					"behaviors": {},
					"world": {
						"x": 392,
						"y": 896,
						"width": 32,
						"height": 16,
						"originX": 0,
						"originY": 0.9375,
						"color": [
							1,
							1,
							1,
							1
						],
						"angle": 0,
						"zElevation": 0
					}
				},
				{
					"type": "Tile_LadderBot",
					"properties": {
						"initially-visible": true,
						"initial-animation": "Wood",
						"initial-frame": 0,
						"enable-collisions": true,
						"live-preview": false
					},
					"uid": 12567,
					"instanceVariables": {
						"Type": "Wood"
					},
					"behaviors": {},
					"world": {
						"x": 392,
						"y": 968,
						"width": 32,
						"height": 8,
						"originX": 0,
						"originY": 0.875,
						"color": [
							1,
							1,
							1,
							1
						],
						"angle": 0,
						"zElevation": 0
					}
				},
				{
					"type": "Tile_Wall",
					"properties": {
						"initially-visible": true,
						"initial-animation": "Default",
						"initial-frame": 2,
						"enable-collisions": true,
						"live-preview": false
					},
					"uid": 12581,
					"instanceVariables": {
						"InitialFrame": 2
					},
					"behaviors": {},
					"world": {
						"x": 280,
						"y": 896,
						"width": 8,
						"height": 8,
						"originX": 0,
						"originY": 1,
						"color": [
							1,
							1,
							1,
							1
						],
						"angle": 0,
						"zElevation": 0
					}
				},
				{
					"type": "Tile_Wall",
					"properties": {
						"initially-visible": true,
						"initial-animation": "Default",
						"initial-frame": 22,
						"enable-collisions": true,
						"live-preview": false
					},
					"uid": 12582,
					"instanceVariables": {
						"InitialFrame": 22
					},
					"behaviors": {},
					"world": {
						"x": 280,
						"y": 888,
						"width": 8,
						"height": 8,
						"originX": 0,
						"originY": 1,
						"color": [
							1,
							1,
							1,
							1
						],
						"angle": 0,
						"zElevation": 0
					}
				},
				{
					"type": "Tile_Wall",
					"properties": {
						"initially-visible": true,
						"initial-animation": "Default",
						"initial-frame": 25,
						"enable-collisions": true,
						"live-preview": false
					},
					"uid": 12585,
					"instanceVariables": {
						"InitialFrame": 25
					},
					"behaviors": {},
					"world": {
						"x": 528,
						"y": 856,
						"width": 8,
						"height": 8,
						"originX": 0,
						"originY": 1,
						"color": [
							1,
							1,
							1,
							1
						],
						"angle": 0,
						"zElevation": 0
					}
				},
				{
					"type": "Tile_Wall",
					"properties": {
						"initially-visible": true,
						"initial-animation": "Default",
						"initial-frame": 26,
						"enable-collisions": true,
						"live-preview": false
					},
					"uid": 12586,
					"instanceVariables": {
						"InitialFrame": 26
					},
					"behaviors": {},
					"world": {
						"x": 280,
						"y": 856,
						"width": 8,
						"height": 8,
						"originX": 0,
						"originY": 1,
						"color": [
							1,
							1,
							1,
							1
						],
						"angle": 0,
						"zElevation": 0
					}
				},
				{
					"type": "Tile_Wall",
					"properties": {
						"initially-visible": true,
						"initial-animation": "Default",
						"initial-frame": 27,
						"enable-collisions": true,
						"live-preview": false
					},
					"uid": 12587,
					"instanceVariables": {
						"InitialFrame": 27
					},
					"behaviors": {},
					"world": {
						"x": 528,
						"y": 864,
						"width": 8,
						"height": 8,
						"originX": 0,
						"originY": 1,
						"color": [
							1,
							1,
							1,
							1
						],
						"angle": 0,
						"zElevation": 0
					}
				},
				{
					"type": "Tile_Wall",
					"properties": {
						"initially-visible": true,
						"initial-animation": "Default",
						"initial-frame": 28,
						"enable-collisions": true,
						"live-preview": false
					},
					"uid": 12588,
					"instanceVariables": {
						"InitialFrame": 28
					},
					"behaviors": {},
					"world": {
						"x": 280,
						"y": 864,
						"width": 8,
						"height": 8,
						"originX": 0,
						"originY": 1,
						"color": [
							1,
							1,
							1,
							1
						],
						"angle": 0,
						"zElevation": 0
					}
				},
				{
					"type": "Tile_Wall",
					"properties": {
						"initially-visible": true,
						"initial-animation": "Default",
						"initial-frame": 29,
						"enable-collisions": true,
						"live-preview": false
					},
					"uid": 12589,
					"instanceVariables": {
						"InitialFrame": 29
					},
					"behaviors": {},
					"world": {
						"x": 528,
						"y": 872,
						"width": 8,
						"height": 8,
						"originX": 0,
						"originY": 1,
						"color": [
							1,
							1,
							1,
							1
						],
						"angle": 0,
						"zElevation": 0
					}
				},
				{
					"type": "Tile_Wall",
					"properties": {
						"initially-visible": true,
						"initial-animation": "Default",
						"initial-frame": 30,
						"enable-collisions": true,
						"live-preview": false
					},
					"uid": 12590,
					"instanceVariables": {
						"InitialFrame": 30
					},
					"behaviors": {},
					"world": {
						"x": 280,
						"y": 872,
						"width": 8,
						"height": 8,
						"originX": 0,
						"originY": 1,
						"color": [
							1,
							1,
							1,
							1
						],
						"angle": 0,
						"zElevation": 0
					}
				},
				{
					"type": "Tile_Wall",
					"properties": {
						"initially-visible": true,
						"initial-animation": "Default",
						"initial-frame": 31,
						"enable-collisions": true,
						"live-preview": false
					},
					"uid": 12591,
					"instanceVariables": {
						"InitialFrame": 31
					},
					"behaviors": {},
					"world": {
						"x": 528,
						"y": 880,
						"width": 8,
						"height": 8,
						"originX": 0,
						"originY": 1,
						"color": [
							1,
							1,
							1,
							1
						],
						"angle": 0,
						"zElevation": 0
					}
				},
				{
					"type": "Tile_Wall",
					"properties": {
						"initially-visible": true,
						"initial-animation": "Default",
						"initial-frame": 32,
						"enable-collisions": true,
						"live-preview": false
					},
					"uid": 12592,
					"instanceVariables": {
						"InitialFrame": 32
					},
					"behaviors": {},
					"world": {
						"x": 280,
						"y": 880,
						"width": 8,
						"height": 8,
						"originX": 0,
						"originY": 1,
						"color": [
							1,
							1,
							1,
							1
						],
						"angle": 0,
						"zElevation": 0
					}
				},
				{
					"type": "Tile_Wall",
					"properties": {
						"initially-visible": true,
						"initial-animation": "Default",
						"initial-frame": 3,
						"enable-collisions": true,
						"live-preview": false
					},
					"uid": 12611,
					"instanceVariables": {
						"InitialFrame": 3
					},
					"behaviors": {},
					"world": {
						"x": 528,
						"y": 912,
						"width": 8,
						"height": 8,
						"originX": 0,
						"originY": 1,
						"color": [
							1,
							1,
							1,
							1
						],
						"angle": 0,
						"zElevation": 0
					}
				},
				{
					"type": "Tile_Wall",
					"properties": {
						"initially-visible": true,
						"initial-animation": "Default",
						"initial-frame": 7,
						"enable-collisions": true,
						"live-preview": false
					},
					"uid": 12612,
					"instanceVariables": {
						"InitialFrame": 7
					},
					"behaviors": {},
					"world": {
						"x": 528,
						"y": 904,
						"width": 8,
						"height": 8,
						"originX": 0,
						"originY": 1,
						"color": [
							1,
							1,
							1,
							1
						],
						"angle": 0,
						"zElevation": 0
					}
				},
				{
					"type": "Tile_Wall",
					"properties": {
						"initially-visible": true,
						"initial-animation": "Default",
						"initial-frame": 3,
						"enable-collisions": true,
						"live-preview": false
					},
					"uid": 12613,
					"instanceVariables": {
						"InitialFrame": 3
					},
					"behaviors": {},
					"world": {
						"x": 528,
						"y": 896,
						"width": 8,
						"height": 8,
						"originX": 0,
						"originY": 1,
						"color": [
							1,
							1,
							1,
							1
						],
						"angle": 0,
						"zElevation": 0
					}
				},
				{
					"type": "Tile_Wall",
					"properties": {
						"initially-visible": true,
						"initial-animation": "Default",
						"initial-frame": 7,
						"enable-collisions": true,
						"live-preview": false
					},
					"uid": 12614,
					"instanceVariables": {
						"InitialFrame": 7
					},
					"behaviors": {},
					"world": {
						"x": 528,
						"y": 888,
						"width": 8,
						"height": 8,
						"originX": 0,
						"originY": 1,
						"color": [
							1,
							1,
							1,
							1
						],
						"angle": 0,
						"zElevation": 0
					}
				},
				{
					"type": "Tile_Ladder",
					"properties": {
						"initially-visible": true,
						"initial-animation": "Wood",
						"initial-frame": 0,
						"enable-collisions": true,
						"live-preview": false
					},
					"uid": 12547,
					"instanceVariables": {
						"Type": "Wood"
					},
					"behaviors": {},
					"world": {
						"x": 392,
						"y": 928,
						"width": 32,
						"height": 32,
						"originX": 0,
						"originY": 0.96875,
						"color": [
							1,
							1,
							1,
							1
						],
						"angle": 0,
						"zElevation": 0
					}
				},
				{
					"type": "Tile_Wall",
					"properties": {
						"initially-visible": true,
						"initial-animation": "Default",
						"initial-frame": 41,
						"enable-collisions": true,
						"live-preview": false
					},
					"uid": 12548,
					"instanceVariables": {
						"InitialFrame": 41
					},
					"behaviors": {},
					"world": {
						"x": 457,
						"y": 968,
						"width": 36,
						"height": 20,
						"originX": 0,
						"originY": 1,
						"color": [
							1,
							1,
							1,
							1
						],
						"angle": 0,
						"zElevation": 0
					}
				},
				{
					"type": "Tile_Wall",
					"properties": {
						"initially-visible": true,
						"initial-animation": "Default",
						"initial-frame": 160,
						"enable-collisions": true,
						"live-preview": false
					},
					"uid": 12615,
					"instanceVariables": {
						"InitialFrame": 160
					},
					"behaviors": {},
					"world": {
						"x": 488,
						"y": 948,
						"width": -24,
						"height": 15,
						"originX": 0,
						"originY": 1,
						"color": [
							1,
							1,
							1,
							1
						],
						"angle": 0,
						"zElevation": 0
					}
				},
				{
					"type": "Tile_Wall",
					"properties": {
						"initially-visible": true,
						"initial-animation": "Default",
						"initial-frame": 55,
						"enable-collisions": true,
						"live-preview": false
					},
					"uid": 12616,
					"instanceVariables": {
						"InitialFrame": 55
					},
					"behaviors": {},
					"world": {
						"x": 320,
						"y": 968,
						"width": 24,
						"height": 49,
						"originX": 0,
						"originY": 1,
						"color": [
							1,
							1,
							1,
							1
						],
						"angle": 0,
						"zElevation": 0
					}
				},
				{
					"type": "Tile_Shadow",
					"properties": {
						"initially-visible": true,
						"initial-animation": "Default",
						"initial-frame": 0,
						"enable-collisions": true,
						"live-preview": false
					},
					"uid": 12820,
					"instanceVariables": {
						"InitialFrame": 0
					},
					"behaviors": {},
					"world": {
						"x": 280,
						"y": 944,
						"width": 256,
						"height": 40,
						"originX": 0,
						"originY": 1,
						"color": [
							1,
							1,
							1,
							1
						],
						"angle": 0,
						"zElevation": 0
					}
				}
			],
			"sid": 655313352654267,
			"effectTypes": [],
			"isInitiallyVisible": true,
			"color": [
				1,
				1,
				1,
				1
			],
			"backgroundColor": [
				1,
				1,
				1,
				1
			],
			"isTransparent": true,
			"parallaxX": 1,
			"parallaxY": 1,
			"scaleRate": 1,
			"forceOwnTexture": false,
			"useRenderCells": false,
			"blendMode": "normal",
			"global": false
		},
		{
			"name": "Solid",
			"overriden": 0,
			"instances": [
				{
					"type": "Solid",
					"properties": {
						"initially-visible": true,
						"initial-animation": "Default",
						"initial-frame": 0,
						"enable-collisions": true,
						"live-preview": false
					},
					"uid": 12325,
					"instanceVariables": {
						"zz_form": "floor"
					},
					"behaviors": {
						"Solid": {
							"properties": {
								"enabled": true,
								"tags": ""
							}
						},
						"Physics": {
							"properties": {
								"immovable": true,
								"collision-mask": "use-collision-polygon",
								"prevent-rotation": false,
								"density": 1,
								"friction": 0.5,
								"elasticity": 0.2,
								"linear-damping": 0,
								"angular-damping": 0.01,
								"bullet": false,
								"enabled": true
							}
						}
					},
					"world": {
						"x": 1000,
						"y": 1000,
						"width": 2000,
						"height": 64,
						"originX": 0.5,
						"originY": 0.5,
						"color": [
							1,
							1,
							1,
							1
						],
						"angle": 0,
						"zElevation": 0
					}
				},
				{
					"type": "Solid",
					"properties": {
						"initially-visible": true,
						"initial-animation": "Default",
						"initial-frame": 0,
						"enable-collisions": true,
						"live-preview": false
					},
					"uid": 12326,
					"instanceVariables": {
						"zz_form": "floor"
					},
					"behaviors": {
						"Solid": {
							"properties": {
								"enabled": true,
								"tags": ""
							}
						},
						"Physics": {
							"properties": {
								"immovable": true,
								"collision-mask": "use-collision-polygon",
								"prevent-rotation": false,
								"density": 1,
								"friction": 0.5,
								"elasticity": 0.2,
								"linear-damping": 0,
								"angular-damping": 0.01,
								"bullet": false,
								"enabled": true
							}
						}
					},
					"world": {
						"x": -16,
						"y": 511,
						"width": 32,
						"height": 1022,
						"originX": 0.5,
						"originY": 0.5,
						"color": [
							1,
							1,
							1,
							1
						],
						"angle": 0,
						"zElevation": 0
					}
				},
				{
					"type": "Solid2Wall",
					"properties": {
						"initially-visible": true,
						"initial-animation": "Default",
						"initial-frame": 0,
						"enable-collisions": true,
						"live-preview": false
					},
					"uid": 12327,
					"instanceVariables": {
						"zz_form": "floor"
					},
					"behaviors": {
						"Solid": {
							"properties": {
								"enabled": true,
								"tags": ""
							}
						},
						"Physics": {
							"properties": {
								"immovable": true,
								"collision-mask": "use-collision-polygon",
								"prevent-rotation": false,
								"density": 1,
								"friction": 0.5,
								"elasticity": 0.2,
								"linear-damping": 0,
								"angular-damping": 0.01,
								"bullet": false,
								"enabled": true
							}
						}
					},
					"world": {
						"x": 280,
						"y": 912,
						"width": 8,
						"height": 80,
						"originX": 0,
						"originY": 1,
						"color": [
							1,
							1,
							1,
							1
						],
						"angle": 0,
						"zElevation": 0
					}
				},
				{
					"type": "Solid2Wall",
					"properties": {
						"initially-visible": true,
						"initial-animation": "Default",
						"initial-frame": 0,
						"enable-collisions": true,
						"live-preview": false
					},
					"uid": 12328,
					"instanceVariables": {
						"zz_form": "floor"
					},
					"behaviors": {
						"Solid": {
							"properties": {
								"enabled": true,
								"tags": ""
							}
						},
						"Physics": {
							"properties": {
								"immovable": true,
								"collision-mask": "use-collision-polygon",
								"prevent-rotation": false,
								"density": 1,
								"friction": 0.5,
								"elasticity": 0.2,
								"linear-damping": 0,
								"angular-damping": 0.01,
								"bullet": false,
								"enabled": true
							}
						}
					},
					"world": {
						"x": 272,
						"y": 835,
						"width": 8,
						"height": 80,
						"originX": 0,
						"originY": 1,
						"color": [
							1,
							1,
							1,
							1
						],
						"angle": 1.088155746,
						"zElevation": 0
					}
				},
				{
					"type": "Solid2Wall",
					"properties": {
						"initially-visible": true,
						"initial-animation": "Default",
						"initial-frame": 0,
						"enable-collisions": true,
						"live-preview": false
					},
					"uid": 12329,
					"instanceVariables": {
						"zz_form": "floor"
					},
					"behaviors": {
						"Solid": {
							"properties": {
								"enabled": true,
								"tags": ""
							}
						},
						"Physics": {
							"properties": {
								"immovable": true,
								"collision-mask": "use-collision-polygon",
								"prevent-rotation": false,
								"density": 1,
								"friction": 0.5,
								"elasticity": 0.2,
								"linear-damping": 0,
								"angular-damping": 0.01,
								"bullet": false,
								"enabled": true
							}
						}
					},
					"world": {
						"x": 528,
						"y": 912,
						"width": 8,
						"height": 80,
						"originX": 0,
						"originY": 1,
						"color": [
							1,
							1,
							1,
							1
						],
						"angle": 0,
						"zElevation": 0
					}
				},
				{
					"type": "Solid2Wall",
					"properties": {
						"initially-visible": true,
						"initial-animation": "Default",
						"initial-frame": 0,
						"enable-collisions": true,
						"live-preview": false
					},
					"uid": 12330,
					"instanceVariables": {
						"zz_form": "floor"
					},
					"behaviors": {
						"Solid": {
							"properties": {
								"enabled": true,
								"tags": ""
							}
						},
						"Physics": {
							"properties": {
								"immovable": true,
								"collision-mask": "use-collision-polygon",
								"prevent-rotation": false,
								"density": 1,
								"friction": 0.5,
								"elasticity": 0.2,
								"linear-damping": 0,
								"angular-damping": 0.01,
								"bullet": false,
								"enabled": true
							}
						}
					},
					"world": {
						"x": 543,
						"y": 843,
						"width": 8,
						"height": 88,
						"originX": 0,
						"originY": 1,
						"color": [
							1,
							1,
							1,
							1
						],
						"angle": 5.165734712179586,
						"zElevation": 0
					}
				},
				{
					"type": "Solid2Wall",
					"properties": {
						"initially-visible": true,
						"initial-animation": "Default",
						"initial-frame": 0,
						"enable-collisions": true,
						"live-preview": false
					},
					"uid": 12331,
					"instanceVariables": {
						"zz_form": "floor"
					},
					"behaviors": {
						"Solid": {
							"properties": {
								"enabled": true,
								"tags": ""
							}
						},
						"Physics": {
							"properties": {
								"immovable": true,
								"collision-mask": "use-collision-polygon",
								"prevent-rotation": false,
								"density": 1,
								"friction": 0.5,
								"elasticity": 0.2,
								"linear-damping": 0,
								"angular-damping": 0.01,
								"bullet": false,
								"enabled": true
							}
						}
					},
					"world": {
						"x": 336,
						"y": 800,
						"width": 8,
						"height": 136,
						"originX": 0,
						"originY": 1,
						"color": [
							1,
							1,
							1,
							1
						],
						"angle": 1.570796371,
						"zElevation": 0
					}
				},
				{
					"type": "Solid2Wall",
					"properties": {
						"initially-visible": true,
						"initial-animation": "Default",
						"initial-frame": 0,
						"enable-collisions": true,
						"live-preview": false
					},
					"uid": 12568,
					"instanceVariables": {
						"zz_form": "floor"
					},
					"behaviors": {
						"Solid": {
							"properties": {
								"enabled": true,
								"tags": ""
							}
						},
						"Physics": {
							"properties": {
								"immovable": true,
								"collision-mask": "use-collision-polygon",
								"prevent-rotation": false,
								"density": 1,
								"friction": 0.5,
								"elasticity": 0.2,
								"linear-damping": 0,
								"angular-damping": 0.01,
								"bullet": false,
								"enabled": true
							}
						}
					},
					"world": {
						"x": 288,
						"y": 896,
						"width": 8,
						"height": 104,
						"originX": 0,
						"originY": 1,
						"color": [
							1,
							1,
							1,
							1
						],
						"angle": 1.570796371,
						"zElevation": 0
					}
				},
				{
					"type": "Solid2Wall",
					"properties": {
						"initially-visible": true,
						"initial-animation": "Default",
						"initial-frame": 0,
						"enable-collisions": true,
						"live-preview": false
					},
					"uid": 12569,
					"instanceVariables": {
						"zz_form": "floor"
					},
					"behaviors": {
						"Solid": {
							"properties": {
								"enabled": true,
								"tags": ""
							}
						},
						"Physics": {
							"properties": {
								"immovable": true,
								"collision-mask": "use-collision-polygon",
								"prevent-rotation": false,
								"density": 1,
								"friction": 0.5,
								"elasticity": 0.2,
								"linear-damping": 0,
								"angular-damping": 0.01,
								"bullet": false,
								"enabled": true
							}
						}
					},
					"world": {
						"x": 424,
						"y": 896,
						"width": 8,
						"height": 104,
						"originX": 0,
						"originY": 1,
						"color": [
							1,
							1,
							1,
							1
						],
						"angle": 1.570796371,
						"zElevation": 0
					}
				}
			],
			"sid": 852525041711692,
			"effectTypes": [],
			"isInitiallyVisible": true,
			"color": [
				1,
				1,
				1,
				1
			],
			"backgroundColor": [
				1,
				1,
				1,
				1
			],
			"isTransparent": true,
			"parallaxX": 1,
			"parallaxY": 1,
			"scaleRate": 1,
			"forceOwnTexture": false,
			"useRenderCells": false,
			"blendMode": "normal",
			"global": false
		},
		{
			"name": "Objects",
			"overriden": 0,
			"instances": [
				{
					"type": "Door_Range",
					"properties": {
						"initially-visible": false,
						"initial-animation": "Default",
						"initial-frame": 0,
						"enable-collisions": true,
						"live-preview": false
					},
					"uid": 12553,
					"instanceVariables": {
						"OutlineCopy": false,
						"Outlined": false,
						"zzzNearest": false,
						"WorldEnabled": false,
						"WorldBark": "",
						"WorldHoverOutline": true,
						"WorldHoverText": "",
						"WorldCanInteract": true,
						"WorldTouched": false,
						"WorldInteractType": "modify",
						"DoorID": 0
					},
					"behaviors": {},
					"effects": {
						"Outline": {
							"parameters": {
								"Just outline": 0,
								"Width": 1,
								"Color": [
									1,
									1,
									1,
									1
								]
							}
						}
					},
					"world": {
						"x": 258,
						"y": 968,
						"width": 56,
						"height": 56,
						"originX": 0.5,
						"originY": 1,
						"color": [
							1,
							1,
							1,
							1
						],
						"angle": 0,
						"zElevation": 0
					}
				},
				{
					"type": "Door_Range",
					"properties": {
						"initially-visible": false,
						"initial-animation": "Default",
						"initial-frame": 0,
						"enable-collisions": true,
						"live-preview": false
					},
					"uid": 12554,
					"instanceVariables": {
						"OutlineCopy": false,
						"Outlined": false,
						"zzzNearest": false,
						"WorldEnabled": false,
						"WorldBark": "",
						"WorldHoverOutline": true,
						"WorldHoverText": "",
						"WorldCanInteract": true,
						"WorldTouched": false,
						"WorldInteractType": "modify",
						"DoorID": 0
					},
					"behaviors": {},
					"effects": {
						"Outline": {
							"parameters": {
								"Just outline": 0,
								"Width": 1,
								"Color": [
									1,
									1,
									1,
									1
								]
							}
						}
					},
					"world": {
						"x": 504,
						"y": 968,
						"width": 56,
						"height": 56,
						"originX": 0.5,
						"originY": 1,
						"color": [
							1,
							1,
							1,
							1
						],
						"angle": 0,
						"zElevation": 0
					}
				},
				{
					"type": "BuildingEndPoint",
					"properties": {
						"initially-visible": false,
						"initial-animation": "Default",
						"initial-frame": 0,
						"enable-collisions": true,
						"live-preview": false
					},
					"uid": 12555,
					"instanceVariables": {
						"ID": 1
					},
					"behaviors": {},
					"world": {
						"x": 664,
						"y": 968,
						"width": 8,
						"height": 8,
						"originX": 0,
						"originY": 1,
						"color": [
							1,
							1,
							1,
							1
						],
						"angle": 0,
						"zElevation": 0
					}
				},
				{
					"type": "BuildingSpawnPoint",
					"properties": {
						"initially-visible": false,
						"initial-animation": "Default",
						"initial-frame": 0,
						"enable-collisions": true,
						"live-preview": false
					},
					"uid": 12556,
					"instanceVariables": {
						"ID": 1
					},
					"behaviors": {},
					"world": {
						"x": 144,
						"y": 968,
						"width": 8,
						"height": 8,
						"originX": 0,
						"originY": 1,
						"color": [
							1,
							1,
							1,
							1
						],
						"angle": 0,
						"zElevation": 0
					}
				},
				{
					"type": "zzSpawn_Vendor",
					"properties": {
						"initially-visible": false,
						"initial-animation": "Default",
						"initial-frame": 0,
						"enable-collisions": true,
						"live-preview": false
					},
					"uid": 12557,
					"instanceVariables": {
						"Type": 50,
						"Label": "Scientist",
						"Diag": "Yeet"
					},
					"behaviors": {},
					"world": {
						"x": 448,
						"y": 968,
						"width": 24,
						"height": 44,
						"originX": 0.5,
						"originY": 1,
						"color": [
							1,
							1,
							1,
							1
						],
						"angle": 0,
						"zElevation": 0
					}
				},
				{
					"type": "zzSpawn_Vendor",
					"properties": {
						"initially-visible": false,
						"initial-animation": "Default",
						"initial-frame": 0,
						"enable-collisions": true,
						"live-preview": false
					},
					"uid": 12559,
					"instanceVariables": {
						"Type": 51,
						"Label": "Medic",
						"Diag": "Yeet"
					},
					"behaviors": {},
					"world": {
						"x": 336,
						"y": 896,
						"width": 24,
						"height": 44,
						"originX": 0.5,
						"originY": 1,
						"color": [
							1,
							1,
							1,
							1
						],
						"angle": 0,
						"zElevation": 0
					}
				},
				{
					"type": "Ladder",
					"properties": {
						"initially-visible": false,
						"initial-animation": "Default",
						"initial-frame": 0,
						"enable-collisions": true,
						"live-preview": false
					},
					"uid": 12580,
					"instanceVariables": {},
					"behaviors": {},
					"world": {
						"x": 408,
						"y": 968,
						"width": 1,
						"height": 72,
						"originX": 0,
						"originY": 1,
						"color": [
							1,
							1,
							1,
							1
						],
						"angle": 0,
						"zElevation": 0
					}
				},
				{
					"type": "JumpThrough",
					"properties": {
						"initially-visible": false,
						"initial-animation": "Default",
						"initial-frame": 0,
						"enable-collisions": true,
						"live-preview": false
					},
					"uid": 12619,
					"instanceVariables": {},
					"behaviors": {
						"Jumpthru": {
							"properties": {
								"enabled": true
							}
						}
					},
					"world": {
						"x": 392,
						"y": 904,
						"width": 32,
						"height": 8,
						"originX": 0,
						"originY": 1,
						"color": [
							1,
							1,
							1,
							1
						],
						"angle": 0,
						"zElevation": 0
					}
				},
				{
					"type": "UpgradeSign",
					"properties": {
						"initially-visible": true,
						"initial-animation": "Default",
						"initial-frame": 0,
						"enable-collisions": true,
						"live-preview": false
					},
					"uid": 12617,
					"instanceVariables": {
						"Cost": 10,
						"Label": "3",
						"TextID": 0
					},
					"behaviors": {},
					"world": {
						"x": 368,
						"y": 968,
						"width": 24,
						"height": 24,
						"originX": 0.5,
						"originY": 1,
						"color": [
							1,
							1,
							1,
							1
						],
						"angle": 0,
						"zElevation": 0
					}
				},
				{
					"type": "zzSpawn_Vendor",
					"properties": {
						"initially-visible": false,
						"initial-animation": "Default",
						"initial-frame": 0,
						"enable-collisions": true,
						"live-preview": false
					},
					"uid": 12558,
					"instanceVariables": {
						"Type": 52,
						"Label": "Ammo",
						"Diag": "Yeet"
					},
					"behaviors": {},
					"world": {
						"x": 480,
						"y": 896,
						"width": -24,
						"height": 44,
						"originX": 0.5,
						"originY": 1,
						"color": [
							1,
							1,
							1,
							1
						],
						"angle": 0,
						"zElevation": 0
					}
				},
				{
					"type": "Spawn_Survivor",
					"properties": {
						"initially-visible": false,
						"initial-animation": "Default",
						"initial-frame": 0,
						"enable-collisions": true,
						"live-preview": false
					},
					"uid": 13090,
					"instanceVariables": {},
					"behaviors": {},
					"world": {
						"x": 184,
						"y": 968,
						"width": 24,
						"height": 44,
						"originX": 0.5,
						"originY": 1,
						"color": [
							1,
							1,
							1,
							1
						],
						"angle": 0,
						"zElevation": 0
					}
				},
				{
					"type": "Spawn_Survivor",
					"properties": {
						"initially-visible": false,
						"initial-animation": "Default",
						"initial-frame": 0,
						"enable-collisions": true,
						"live-preview": false
					},
					"uid": 13103,
					"instanceVariables": {},
					"behaviors": {},
					"world": {
						"x": 240,
						"y": 968,
						"width": 24,
						"height": 44,
						"originX": 0.5,
						"originY": 1,
						"color": [
							1,
							1,
							1,
							1
						],
						"angle": 0,
						"zElevation": 0
					}
				},
				{
					"type": "Spawn_Survivor",
					"properties": {
						"initially-visible": false,
						"initial-animation": "Default",
						"initial-frame": 0,
						"enable-collisions": true,
						"live-preview": false
					},
					"uid": 13104,
					"instanceVariables": {},
					"behaviors": {},
					"world": {
						"x": 216,
						"y": 968,
						"width": 24,
						"height": 44,
						"originX": 0.5,
						"originY": 1,
						"color": [
							1,
							1,
							1,
							1
						],
						"angle": 0,
						"zElevation": 0
					}
				},
				{
					"type": "Spawn_Survivor",
					"properties": {
						"initially-visible": false,
						"initial-animation": "Default",
						"initial-frame": 0,
						"enable-collisions": true,
						"live-preview": false
					},
					"uid": 13105,
					"instanceVariables": {},
					"behaviors": {},
					"world": {
						"x": 200,
						"y": 968,
						"width": 24,
						"height": 44,
						"originX": 0.5,
						"originY": 1,
						"color": [
							1,
							1,
							1,
							1
						],
						"angle": 0,
						"zElevation": 0
					}
				},
				{
					"type": "Spawn_Survivor",
					"properties": {
						"initially-visible": false,
						"initial-animation": "Default",
						"initial-frame": 0,
						"enable-collisions": true,
						"live-preview": false
					},
					"uid": 13106,
					"instanceVariables": {},
					"behaviors": {},
					"world": {
						"x": 256,
						"y": 968,
						"width": 24,
						"height": 44,
						"originX": 0.5,
						"originY": 1,
						"color": [
							1,
							1,
							1,
							1
						],
						"angle": 0,
						"zElevation": 0
					}
				},
				{
					"type": "Spawn_Survivor",
					"properties": {
						"initially-visible": false,
						"initial-animation": "Default",
						"initial-frame": 0,
						"enable-collisions": true,
						"live-preview": false
					},
					"uid": 13107,
					"instanceVariables": {},
					"behaviors": {},
					"world": {
						"x": 568,
						"y": 968,
						"width": 24,
						"height": 44,
						"originX": 0.5,
						"originY": 1,
						"color": [
							1,
							1,
							1,
							1
						],
						"angle": 0,
						"zElevation": 0
					}
				},
				{
					"type": "Spawn_Survivor",
					"properties": {
						"initially-visible": false,
						"initial-animation": "Default",
						"initial-frame": 0,
						"enable-collisions": true,
						"live-preview": false
					},
					"uid": 13108,
					"instanceVariables": {},
					"behaviors": {},
					"world": {
						"x": 624,
						"y": 968,
						"width": 24,
						"height": 44,
						"originX": 0.5,
						"originY": 1,
						"color": [
							1,
							1,
							1,
							1
						],
						"angle": 0,
						"zElevation": 0
					}
				},
				{
					"type": "Spawn_Survivor",
					"properties": {
						"initially-visible": false,
						"initial-animation": "Default",
						"initial-frame": 0,
						"enable-collisions": true,
						"live-preview": false
					},
					"uid": 13109,
					"instanceVariables": {},
					"behaviors": {},
					"world": {
						"x": 600,
						"y": 968,
						"width": 24,
						"height": 44,
						"originX": 0.5,
						"originY": 1,
						"color": [
							1,
							1,
							1,
							1
						],
						"angle": 0,
						"zElevation": 0
					}
				},
				{
					"type": "Spawn_Survivor",
					"properties": {
						"initially-visible": false,
						"initial-animation": "Default",
						"initial-frame": 0,
						"enable-collisions": true,
						"live-preview": false
					},
					"uid": 13110,
					"instanceVariables": {},
					"behaviors": {},
					"world": {
						"x": 584,
						"y": 968,
						"width": 24,
						"height": 44,
						"originX": 0.5,
						"originY": 1,
						"color": [
							1,
							1,
							1,
							1
						],
						"angle": 0,
						"zElevation": 0
					}
				},
				{
					"type": "Spawn_Survivor",
					"properties": {
						"initially-visible": false,
						"initial-animation": "Default",
						"initial-frame": 0,
						"enable-collisions": true,
						"live-preview": false
					},
					"uid": 13111,
					"instanceVariables": {},
					"behaviors": {},
					"world": {
						"x": 640,
						"y": 968,
						"width": 24,
						"height": 44,
						"originX": 0.5,
						"originY": 1,
						"color": [
							1,
							1,
							1,
							1
						],
						"angle": 0,
						"zElevation": 0
					}
				},
				{
					"type": "Stats_Board",
					"properties": {
						"initially-visible": true,
						"initial-animation": "Default",
						"initial-frame": 0,
						"enable-collisions": true,
						"live-preview": false
					},
					"uid": 13112,
					"instanceVariables": {
						"Cost": 10
					},
					"behaviors": {},
					"world": {
						"x": 684,
						"y": 968,
						"width": -24,
						"height": 24,
						"originX": 0.5,
						"originY": 1,
						"color": [
							1,
							1,
							1,
							1
						],
						"angle": 0,
						"zElevation": 0
					}
				}
			],
			"sid": 171525081699434,
			"effectTypes": [],
			"isInitiallyVisible": true,
			"color": [
				1,
				1,
				1,
				1
			],
			"backgroundColor": [
				1,
				1,
				1,
				1
			],
			"isTransparent": true,
			"parallaxX": 1,
			"parallaxY": 1,
			"scaleRate": 1,
			"forceOwnTexture": false,
			"useRenderCells": false,
			"blendMode": "normal",
			"global": false
		},
		{
			"name": "Player",
			"overriden": 0,
			"instances": [
				{
					"type": "Spawn_Player",
					"properties": {
						"initially-visible": false,
						"initial-animation": "Default",
						"initial-frame": 0,
						"enable-collisions": true,
						"live-preview": false
					},
					"uid": 12560,
					"instanceVariables": {},
					"behaviors": {},
					"world": {
						"x": 16,
						"y": 968,
						"width": 30,
						"height": 45,
						"originX": 0.533333,
						"originY": 1,
						"color": [
							1,
							1,
							1,
							1
						],
						"angle": 0,
						"zElevation": 0
					}
				}
			],
			"sid": 351875421431987,
			"effectTypes": [],
			"isInitiallyVisible": true,
			"color": [
				1,
				1,
				1,
				1
			],
			"backgroundColor": [
				1,
				1,
				1,
				1
			],
			"isTransparent": true,
			"parallaxX": 1,
			"parallaxY": 1,
			"scaleRate": 1,
			"forceOwnTexture": false,
			"useRenderCells": false,
			"blendMode": "normal",
			"global": false
		},
		{
			"name": "Fog",
			"overriden": 0,
			"instances": [],
			"sid": 953755256622232,
			"effectTypes": [],
			"isInitiallyVisible": true,
			"color": [
				1,
				1,
				1,
				1
			],
			"backgroundColor": [
				1,
				1,
				1,
				1
			],
			"isTransparent": true,
			"parallaxX": 1,
			"parallaxY": 1,
			"scaleRate": 1,
			"forceOwnTexture": true,
			"useRenderCells": false,
			"blendMode": "normal",
			"global": false
		}
	],
	"sid": 726083775624000,
	"nonworld-instances": [],
	"effectTypes": [],
	"width": 2000,
	"height": 1000,
	"unboundedScrolling": false,
	"eventSheet": "LevelBuilder_E"
}